bank/__init__.py
bank/admin.py
bank/apps.py
bank/factories.py
bank/fields.py
bank/managers.py
bank/models.py
bank/tests.py
bank/fixtures/initial_bank.json
bank/fixtures/rename_banks.json
bank/migrations/0001_initial.py
bank/migrations/0002_load_initial_data.py
bank/migrations/0003_rename_banks.py
bank/migrations/__init__.py
bank/templates/admin/bank/bank_changelist.html
bank/templates/admin/bank/bank_import_csv.html
p1_bank-0.5.0.dist-info/LICENSE
p1_bank-0.5.0.dist-info/METADATA
p1_bank-0.5.0.dist-info/WHEEL
p1_bank-0.5.0.dist-info/top_level.txt
p1_bank-0.5.0.dist-info/RECORD
