Metadata-Version: 2.1
Name: p1-bank
Version: 0.5.0
Summary: A simple Django app that provides Indonesian Bank models and fields.
Author: Yonas Adiel
Author-email: engineering@dekoruma.com
License: MIT
Classifier: Environment :: Web Environment
Classifier: Framework :: Django
Classifier: Framework :: Django :: 1.11
Classifier: Intended Audience :: Developers
Classifier: Operating System :: OS Independent
Classifier: Programming Language :: Python
Classifier: Programming Language :: Python :: 2.7
Classifier: Topic :: Internet :: WWW/HTTP
Classifier: Topic :: Internet :: WWW/HTTP :: Dynamic Content
License-File: LICENSE
Requires-Dist: factory-boy >=3.0.0
